daddy/__init__.py
daddy/__main__.py
daddy_config/__init__.py
daddy_config/__main__.py
mommy/__init__.py
mommy/__main__.py
mommy_config/__init__.py
mommy_config/__main__.py
python_mommy/__init__.py
python_mommy/__main__.py
python_mommy/responses.json
python_mommy/utils.py
python_mommy/config/__init__.py
python_mommy/config/structure.py
python_mommy/config/utils.py
python_mommy/programs/__init__.py
python_mommy/programs/patch.py
python_mommy/programs/shell.py
python_mommy_venv-1.0.2.dist-info/METADATA
python_mommy_venv-1.0.2.dist-info/WHEEL
python_mommy_venv-1.0.2.dist-info/licenses/LICENSE
python_mommy_venv-1.0.2.dist-info/RECORD
