Metadata-Version: 2.4
Name: python_mommy_venv
Version: 1.0.2
Summary: Mommy's here to support you when running python~ ❤️ [rewrite of python-mommy] [compatible with cargo-mommy]
Project-URL: Homepage, https://github.com/acute-interpreter-panic/python-mommy-venv
Project-URL: Issues, https://github.com/acute-interpreter-panic/python-mommy-venv/issues
Author-email: Acute Interpreter Panic <acute_interpreter_panic@proton.me>
License-File: LICENSE
Classifier: License :: OSI Approved :: MIT License
Classifier: Operating System :: OS Independent
Classifier: Programming Language :: Python :: 3
Requires-Python: >=3.10
Requires-Dist: requests
Requires-Dist: toml
Requires-Dist: typing-extensions
Requires-Dist: xdg-base-dirs
